setup.py
briton_damassa/__init__.py
briton_damassa/debug.py
debugdamassa_briton.egg-info/PKG-INFO
debugdamassa_briton.egg-info/SOURCES.txt
debugdamassa_briton.egg-info/dependency_links.txt
debugdamassa_briton.egg-info/top_level.txt