Metadata-Version: 1.1
Name: debugdamassa-briton
Version: 0.0.2
Summary: Fatec CI/CD Example
Home-page: https://github.com/Lucs1590/TestDebug
Author: Lucas de Brito Silva
Author-email: lucasbsilva29@gmail.com
License: BSD
Download-URL: https://github.com/Lucs1590/TestDebug
Keywords: damassa,debug
Platform: UNKNOWN
Classifier: Operating System :: OS Independent
Classifier: Programming Language :: Python :: 2
Classifier: Programming Language :: Python :: 3
Classifier: Development Status :: 3 - Alpha
Classifier: License :: OSI Approved :: BSD License
